[
  {
    "id": "context-engine-v2",
    "date": "2026-03-31",
    "title": "שיפורי מערכת הקשרים בשיחה",
    "subtitle": "7 שיפורים למערכת ה-context — לימור זוכרת טוב יותר",
    "stats": {
      "improvements": 7,
      "linesOfCode": 894,
      "files": 11,
      "tests": 460
    },
    "items": [
      {
        "number": 1,
        "title": "שמירת מצב שיחה ב-SQLite",
        "impactHigh": true,
        "complexityLow": true,
        "problem": "מצב השיחה נמחק בכל restart של PM2 — לימור \"שוכחת\" שהיא באמצע משהו",
        "solution": "העברת ה-state store מ-Map בזיכרון לטבלת SQLite שמחזיקה מעמד",
        "detail": "עכשיו אם לימור ממתינה לפרטים מהמשתמש, ממתינה לאישור מהבעלים, או באמצע תהליך פגישה — היא זוכרת את זה גם אחרי restart."
      },
      {
        "number": 2,
        "title": "בחירה חכמה של היסטוריה",
        "impactHigh": true,
        "complexityLow": false,
        "problem": "כל 200 ההודעות נשלחות לקלוד — רובן לא רלוונטיות, בזבוז tokens ורעש",
        "solution": "אלגוריתם דטרמיניסטי שבוחר ~60 הודעות רלוונטיות מתוך 200",
        "detail": "תמיד כולל: 20 הודעות אחרונות + הודעות עם שמות/ישויות מההודעה הנוכחית + הודעות עם שימוש בכלים. שאר ההודעות מקבלות ניקוד לפי: חפיפת מילות מפתח, קרבה זמנית, נוכחות החלטות ותאריכים. חיסכון של ~70% ב-input tokens."
      },
      {
        "number": 3,
        "title": "סיכום מובנה (Structured Summary)",
        "impactHigh": false,
        "complexityLow": true,
        "problem": "הסיכום הרולינג הוא 10 שורות טקסט חופשי — מאבד שמות, תאריכים והחלטות עם כל סיבוב",
        "solution": "פורמט JSON מובנה שמשמר פרטים ספציפיים לאורך זמן",
        "detail": "הסיכום כולל עכשיו: activeTopic, recentDecisions, openCommitments, keyPeople, narrative. שמות ותאריכים כבר לא נאבדים בדחיסה."
      },
      {
        "number": 4,
        "title": "פרקי שיחה (Topic Segments)",
        "impactHigh": true,
        "complexityLow": false,
        "problem": "\"זוכרת שדיברנו על הטיול ליוון?\" — לימור לא יכולה לשחזר שיחות ישנות",
        "solution": "חילוץ \"פרקי שיחה\" מובנים עם נושא, סיכום, אנשים, החלטות ותאריכים — ניתנים לחיפוש",
        "detail": "כשהודעות נגזרות מההיסטוריה, Sonnet מחלץ 1-3 סגמנטים ושומר ב-SQLite (עד 50 לכל שיחה). בכל הודעה נכנסת, 3 סגמנטים רלוונטיים מוזרקים להקשר. עכשיו לימור באמת \"זוכרת\" שיחות מלפני שבועות."
      },
      {
        "number": 5,
        "title": "שיפור Reference Resolution",
        "impactHigh": false,
        "complexityLow": true,
        "problem": "לימור לא מבינה \"הדבר ההוא שדיברנו עליו\", \"המסעדה ההיא\", \"אתמול\"",
        "solution": "הרחבת ה-resolver עם חיפוש ב-topic segments, memory, והפניות זמניות",
        "detail": "תבניות חדשות: \"מה שדיברנו עליו\" → סגמנט אחרון, \"המסעדה ההיא\" → חיפוש לפי ישות, \"אתמול\"/\"בשבוע שעבר\" → סגמנטים לפי זמן. הכל דטרמיניסטי, בלי קריאות AI."
      },
      {
        "number": 6,
        "title": "שיפור הקשר בקבוצות",
        "impactHigh": false,
        "complexityLow": false,
        "problem": "רק \"הודעה אחרונה\" ומונה הודעות לכל אדם בקבוצה — הקשר מינימלי",
        "solution": "מעקב אחרי 5 נושאים אחרונים לכל אדם + מי מדבר עם מי",
        "detail": "עכשיו לימור יודעת: על מה כל אדם דיבר לאחרונה (5 נושאים), עם מי הוא מתקשר בקבוצה, ומה דינמיקת השיחה."
      },
      {
        "number": 7,
        "title": "שחזור הקשר אחרי Restart",
        "impactHigh": false,
        "complexityLow": true,
        "problem": "אחרי restart, גם עם SQLite state, ההקשר המלא (extraContext) אובד",
        "solution": "שמירת snapshot של ההקשר האחרון + הזרקתו בהודעה הראשונה אחרי restart",
        "detail": "ה-context snapshot נשמר ב-SQLite אחרי כל הודעה. אחרי restart, אם ה-snapshot עדכני (עד שעתיים), הוא מוזרק להקשר. לימור חוזרת לעבודה כאילו כלום לא קרה."
      }
    ]
  }
]
